README.rst
setup.py
yaipopt/__init__.py
yaipopt/wrapper.pyx
yaipopt.egg-info/PKG-INFO
yaipopt.egg-info/SOURCES.txt
yaipopt.egg-info/dependency_links.txt
yaipopt.egg-info/requires.txt
yaipopt.egg-info/top_level.txt