Metadata-Version: 1.1
Name: yaipopt
Version: 0.1.dev1
Summary: Python bindings for IPOPT nonlinear optimization solver.
Home-page: http://github.com/dimasad/yaipopt
Author: Dimas Abreu Dutra
Author-email: dimasad@ufmg.br
License: MIT
Platform: Windows
Platform: Linux
Platform: Solaris
Platform: Mac OS-X
Platform: Unix
Classifier: Intended Audience :: Developers
Classifier: Intended Audience :: Science/Research
Classifier: License :: OSI Approved
Classifier: Operating System :: MacOS
Classifier: Operating System :: Microsoft :: Windows
Classifier: Operating System :: POSIX
Classifier: Operating System :: Unix
Classifier: Programming Language :: Python
Classifier: Programming Language :: Python :: 3
Classifier: Topic :: Scientific/Engineering
Classifier: Topic :: Software Development
